gv/__init__.py
gv/entry.py
gitverbose-0.5.dist-info/LICENSE.txt
gitverbose-0.5.dist-info/METADATA
gitverbose-0.5.dist-info/WHEEL
gitverbose-0.5.dist-info/entry_points.txt
gitverbose-0.5.dist-info/top_level.txt
gitverbose-0.5.dist-info/RECORD
